peakdet/__init__.py
peakdet/_version.py
peakdet/analytics.py
peakdet/editor.py
peakdet/external.py
peakdet/io.py
peakdet/modalities.py
peakdet/operations.py
peakdet/physio.py
peakdet/utils.py
peakdet/cli/__init__.py
peakdet/cli/run.py
peakdet/tests/__init__.py
peakdet/tests/conftest.py
peakdet/tests/test_analytics.py
peakdet/tests/test_editor.py
peakdet/tests/test_external.py
peakdet/tests/test_io.py
peakdet/tests/test_operations.py
peakdet/tests/test_physio.py
peakdet/tests/test_utils.py
peakdet/tests/utils.py
peakdet/tests/data/ECG.csv
peakdet/tests/data/ECG.phys
peakdet/tests/data/PPG.csv
peakdet/tests/data/RESP.csv
peakdet/tests/data/header.csv
peakdet/tests/data/history.json
peakdet/tests/data/rtpeaks.csv
peakdet-0.5.2.dist-info/LICENSE
peakdet-0.5.2.dist-info/METADATA
peakdet-0.5.2.dist-info/WHEEL
peakdet-0.5.2.dist-info/top_level.txt
peakdet-0.5.2.dist-info/RECORD
