Metadata-Version: 2.1
Name: peakdet
Version: 0.5.2
Summary: A Python toolbox for the identification and processing of peaks and troughs in physiological data
Home-page: https://github.com/physiopy/peakdet
Download-URL: https://github.com/physiopy/peakdet
Author: Ross Markello, The Physiopy Community
Maintainer: The Physiopy Community
Maintainer-email: rossmarkello@gmail.com, physiopy.community@gmail.com
License: Apache-2.0
Platform: OS Independent
Classifier: Development Status :: 4 - Beta
Classifier: Intended Audience :: Science/Research
Classifier: License :: OSI Approved :: Apache Software License
Classifier: Programming Language :: Python :: 3
Provides: peakdet
Requires-Python: >=3.6.1
License-File: LICENSE
Requires-Dist: matplotlib>=3.1.1
Requires-Dist: numpy>=1.9.3
Requires-Dist: scipy
Requires-Dist: loguru
Provides-Extra: all
Requires-Dist: pandas; extra == "all"
Requires-Dist: sphinx>=2.0; extra == "all"
Requires-Dist: sphinx-argparse; extra == "all"
Requires-Dist: sphinx-rtd-theme; extra == "all"
Requires-Dist: duecredit; extra == "all"
Requires-Dist: flake8>=3.7; extra == "all"
Requires-Dist: flake8-docstrings>=1.5; extra == "all"
Requires-Dist: black; extra == "all"
Requires-Dist: isort<6.0.0; extra == "all"
Requires-Dist: pydocstyle; extra == "all"
Requires-Dist: codespell; extra == "all"
Requires-Dist: pytest>=5.3; extra == "all"
Requires-Dist: pytest-cov; extra == "all"
Provides-Extra: dev
Requires-Dist: pandas; extra == "dev"
Requires-Dist: sphinx>=2.0; extra == "dev"
Requires-Dist: sphinx-argparse; extra == "dev"
Requires-Dist: sphinx-rtd-theme; extra == "dev"
Requires-Dist: duecredit; extra == "dev"
Requires-Dist: flake8>=3.7; extra == "dev"
Requires-Dist: flake8-docstrings>=1.5; extra == "dev"
Requires-Dist: black; extra == "dev"
Requires-Dist: isort<6.0.0; extra == "dev"
Requires-Dist: pydocstyle; extra == "dev"
Requires-Dist: codespell; extra == "dev"
Requires-Dist: pytest>=5.3; extra == "dev"
Requires-Dist: pytest-cov; extra == "dev"
Requires-Dist: pre-commit; extra == "dev"
Provides-Extra: doc
Requires-Dist: pandas; extra == "doc"
Requires-Dist: sphinx>=2.0; extra == "doc"
Requires-Dist: sphinx-argparse; extra == "doc"
Requires-Dist: sphinx-rtd-theme; extra == "doc"
Provides-Extra: duecredit
Requires-Dist: duecredit; extra == "duecredit"
Provides-Extra: enhgui
Requires-Dist: Gooey; extra == "enhgui"
Requires-Dist: wxpython; extra == "enhgui"
Provides-Extra: nk
Requires-Dist: pandas; extra == "nk"
Provides-Extra: style
Requires-Dist: flake8>=3.7; extra == "style"
Requires-Dist: flake8-docstrings>=1.5; extra == "style"
Requires-Dist: black; extra == "style"
Requires-Dist: isort<6.0.0; extra == "style"
Requires-Dist: pydocstyle; extra == "style"
Requires-Dist: codespell; extra == "style"
Provides-Extra: test
Requires-Dist: pytest>=5.3; extra == "test"
Requires-Dist: pytest-cov; extra == "test"
Requires-Dist: flake8>=3.7; extra == "test"
Requires-Dist: flake8-docstrings>=1.5; extra == "test"
Requires-Dist: black; extra == "test"
Requires-Dist: isort<6.0.0; extra == "test"
Requires-Dist: pydocstyle; extra == "test"
Requires-Dist: codespell; extra == "test"
Requires-Dist: pandas; extra == "test"
